wrap/__init__.py
wrap/_wrap_py_launcher.py
wrap/w1.py
CoursePythonAdult_ru-0.1.3.1.dist-info/METADATA
CoursePythonAdult_ru-0.1.3.1.dist-info/WHEEL
CoursePythonAdult_ru-0.1.3.1.dist-info/top_level.txt
CoursePythonAdult_ru-0.1.3.1.dist-info/RECORD
